Workbook

Sheet Costi x asset
B1: HOTEL | N1: *** | P1: RESIDENCE
B2: PERSONALE | E2: PRODUZIONE | H2: GESTIONE E FIN. | K2: COMMERCIAL. | P2: PERSONALE | S2: PRODUZIONE | V2: GESTIONE E FIN. | Y2: COMMERCIAL.
A3: COSTI | B3: 2024 | C3: 2025 | D3: budget | E3: 2024 | F3: 2025 | G3: Budget | H3: 2024 | I3: 2025 | J3: Budget | K3: 2024 | M3: Budget | O3: COSTI | P3: 2024 | Q3: 2025 | R3: budget | S3: 2024 | T3: 2025 | U3: Budget | V3: 2024 | W3: 2025 | X3: Budget | Y3: 2024 | Z3: 2025 | AA3: Budget
A4: Gennaio | O4: Gennaio
A5: Febbraio | O5: Febbraio
A6: Marzo | O6: Marzo
A7: Aprile | O7: Aprile
A8: Maggio | O8: Maggio
A9: Giugno | O9: Giugno
A10: Luglio | O10: Luglio
A11: Agosto | O11: Agosto
A12: Settembre | O12: Settembre
A13: Ottobre | O13: Ottobre
A14: Novembre | O14: Novembre
A15: Dicembre | O15: Dicembre
A16: TOTALI | B16: =SUM(B4:B15) -> 0 | C16: =SUM(C4:C15) -> 0 | D16: =SUM(D4:D15) -> 0 | E16: =SUM(E4:E15) -> 0 | F16: =SUM(F4:F15) -> 0 | G16: =SUM(G4:G15) -> 0 | H16: =SUM(H4:H15) -> 0 | I16: =SUM(I4:I15) -> 0 | ... M16: =SUM(M4:M15) -> 0 | O16: TOTALI | P16: =SUM(P4:P15) -> 0 | Q16: =SUM(Q4:Q15) -> 0 | R16: =SUM(R4:R15) -> 0 | S16: =SUM(S4:S15) -> 0 | T16: =SUM(T4:T15) -> 0 | U16: =SUM(U4:U15) -> 0 | V16: =SUM(V4:V15) -> 0 | W16: =SUM(W4:W15) -> 0 | ... AA16: =SUM(AA4:AA15) -> 0
A17: incidenza sui costi totali | B17: =B16/'costi-ricavi totali'!B17 -> #DIV/0! | C17: =C16/'costi-ricavi totali'!C17 -> #DIV/0! | D17: =D16/'costi-ricavi totali'!D17 -> #DIV/0! | E17: =E16/'costi-ricavi totali'!B17 -> #DIV/0! | F17: =F16/'costi-ricavi totali'!C17 -> #DIV/0! | G17: =G16/'costi-ricavi totali'!D17 -> #DIV/0! | H17: =H16/'costi-ricavi totali'!B17 -> #DIV/0! | I17: =I16/'costi-ricavi totali'!C17 -> #DIV/0! | J17: =J16/'costi-ricavi totali'!D17 -> #DIV/0! | K17: =K16/'costi-ricavi totali'!B17 -> #DIV/0! | L17: =L16/'costi-ricavi totali'!C17 -> #DIV/0! | M17: =M16/'costi-ricavi totali'!D17 -> #DIV/0! | O17: incidenza sui costi totali | P17: =P16/'costi-ricavi totali'!$B$17 -> #DIV/0! | Q17: =Q16/'costi-ricavi totali'!$C$17 -> #DIV/0! | R17: =R16/'costi-ricavi totali'!$D$17 -> #DIV/0! | S17: =S16/'costi-ricavi totali'!$B$17 -> #DIV/0! | T17: =T16/'costi-ricavi totali'!$C$17 -> #DIV/0! | U17: =U16/'costi-ricavi totali'!$D$17 -> #DIV/0! | V17: =V16/'costi-ricavi totali'!$B$17 -> #DIV/0! | W17: =W16/'costi-ricavi totali'!$C$17 -> #DIV/0! | X17: =X16/'costi-ricavi totali'!$D$17 -> #DIV/0! | Y17: =Y16/'costi-ricavi totali'!$B$17 -> #DIV/0! | Z17: =Z16/'costi-ricavi totali'!$C$17 -> #DIV/0! | AA17: =AA16/'costi-ricavi totali'!$D$17 -> #DIV/0!
B19: C.V.M. | P19: legenda (ipotesi voci per singolo capitolo di spesa)
B20: PERSONALE | E20: PRODUZIONE | H20: GESTIONE E FIN. | K20: COMMERCIAL. | P20: costi produzione hotel ( tutti i costi variabili in relazione all'erogazione dei servizi e in rapporto ai clienti)
A21: COSTI | B21: 2024 | C21: 2025 | D21: budget | E21: 2024 | F21: 2025 | G21: Budget | H21: 2024 | I21: 2025 | J21: Budget | K21: 2024 | L21: 2025 | M21: Budget | Q21: costi per acquisti materiale( prodotti di consumo per ristorazione e camere)
A22: Gennaio | Q22: costi per manuntenzione di allestimento/rispristino (ottica problem solving)
A23: Febbraio | Q23: costi per lavenderia e biancheria
A24: Marzo | P24: costi gestione e fin. ( tutti i costi che si devono sostenere indipendentemente dal flusso di clienti)
A25: Aprile | Q25: costi affitto o rate del mutuo, tasse sulla proprietà, imposte e licenze
A26: Maggio | Q26: assicurazioni e spese amministrative ( commercialista, software gestionali , cancelleria,consulenti, CCIA Associazione ecc)
A27: Giugno | Q27: manutenzione ordinaria: spese periodiche per la conservazione della struttura e degli impianti
A28: Luglio | Q28: utenze
A29: Agosto | P29: costi commerciali hotel (tutte le spese per la promozione e commercializzazione della struttura)
A30: Settembre | Q30: marketing e pubblicità (eventi, promo, campagne on/off line)
A31: Ottobre | Q31: comunicazione on/off line (gestione social organico, web site, depliant, brand identity, info clienti ecc)
A32: Novembre | Q32: azioni di vendita e commissioni ( costo per sales e relative attività, commissioni on/off line)
A33: Dicembre
A34: TOTALI | B34: =SUM(B22:B33) -> 0 | C34: =SUM(C22:C33) -> 0 | D34: =SUM(D22:D33) -> 0 | E34: =SUM(E22:E33) -> 0 | F34: =SUM(F22:F33) -> 0 | G34: =SUM(G22:G33) -> 0 | H34: =SUM(H22:H33) -> 0 | I34: =SUM(I22:I33) -> 0 | ... M34: =SUM(M22:M33) -> 0
A35: incidenza sui costi totali | B35: =B34/'costi-ricavi totali'!$B$17 -> #DIV/0! | C35: =C34/'costi-ricavi totali'!$C$17 -> #DIV/0! | D35: =D34/'costi-ricavi totali'!$D$17 -> #DIV/0! | E35: =E34/'costi-ricavi totali'!$B$17 -> #DIV/0! | F35: =F34/'costi-ricavi totali'!$C$17 -> #DIV/0! | G35: =G34/'costi-ricavi totali'!$D$17 -> #DIV/0! | H35: =H34/'costi-ricavi totali'!$B$17 -> #DIV/0! | I35: =I34/'costi-ricavi totali'!$C$17 -> #DIV/0! | J35: =J34/'costi-ricavi totali'!$D$17 -> #DIV/0! | K35: =K34/'costi-ricavi totali'!$B$17 -> #DIV/0! | L35: =L34/'costi-ricavi totali'!$C$17 -> #DIV/0! | M35: =M34/'costi-ricavi totali'!$D$17 -> #DIV/0!

Sheet Ricavi Hotel per asset
B1: SOGGIORNI | G1: RISTORANTE | L1: EXTRA | Q1: TOTALI MESE
A2: RICAVI | B2: 2024 | C2: 2025/2024 | D2: 2025 | E2: 2025/Bdg | F2: Budget | G2: 2024 | H2: 2025/2024 | I2: 2025 | J2: 2025/Bdg | K2: Budget | L2: 2024 | M2: 2025/2024 | N2: 2025 | O2: 2025/Bdg | P2: Budget | Q2: 2024 | R2: 2025 | S2: budget
A3: Gennaio | B3: 0 | C3: =(D3-B3)/D3 -> #DIV/0! | D3: 0 | E3: =(D3-F3)/F3 -> #DIV/0! | F3: 0 | G3: 0 | H3: =(I3-G3)/I3 -> #DIV/0! | I3: 0 | J3: =(I3-K3)/K3 -> #DIV/0! | K3: 0 | M3: =(N3-L3)/N3 -> #DIV/0! | N3: 0 | O3: =(N3-P3)/P3 -> #DIV/0! | P3: 0 | Q3: =B3+G3+L3 -> 0 | R3: =D3+I3+N3 -> 0 | S3: =F3+K3+P3 -> 0
A4: Febbraio | B4: 0 | C4: =(D4-B4)/D4 -> #DIV/0! | D4: 0 | E4: =(D4-F4)/F4 -> #DIV/0! | F4: 0 | G4: 0 | H4: =(I4-G4)/I4 -> #DIV/0! | I4: 0 | J4: =(I4-K4)/K4 -> #DIV/0! | K4: 0 | M4: =(N4-L4)/N4 -> #DIV/0! | N4: 0 | O4: =(N4-P4)/P4 -> #DIV/0! | P4: 0 | Q4: =B4+G4+L4 -> 0 | R4: =D4+I4+N4 -> 0 | S4: =F4+K4+P4 -> 0
A5: PROGRESSIVO | B5: =SUM(B3:B4) -> 0 | C5: =(D5-B5)/D5 -> #DIV/0! | D5: =SUM(D3:D4) -> 0 | E5: =(F5-D5)/F5 -> #DIV/0! | F5: =SUM(F3:F4) -> 0 | G5: =SUM(G3:G4) -> 0 | H5: =(I5-G5)/I5 -> #DIV/0! | I5: =SUM(I3:I4) -> 0 | J5: =(I5-K5)/K5 -> #DIV/0! | K5: =SUM(K3:K4) -> 0 | L5: =SUM(L3:L4) -> 0 | M5: =(N5-L5)/N5 -> #DIV/0! | N5: =SUM(N3:N4) -> 0 | O5: =(N5-P5)/P5 -> #DIV/0! | P5: =SUM(P3:P4) -> 0 | Q5: =B5+G5+L5 -> 0 | R5: =D5+I5+N5 -> 0 | S5: =F5+K5+P5 -> 0
A6: Marzo | B6: 0 | C6: =(D6-B6)/D6 -> #DIV/0! | D6: 0 | E6: =(D6-F6)/F6 -> #DIV/0! | F6: 0 | G6: 0 | H6: =(I6-G6)/I6 -> #DIV/0! | I6: 0 | J6: =(I6-K6)/K6 -> #DIV/0! | K6: 0 | M6: =(N6-L6)/N6 -> #DIV/0! | N6: 0 | O6: =(N6-P6)/P6 -> #DIV/0! | P6: 0 | Q6: =B6+G6+L6 -> 0 | R6: =D6+I6+N6 -> 0 | S6: =F6+K6+P6 -> 0
A7: PROGRESSIVO | B7: =SUM(B5:B6) -> 0 | C7: =(D7-B7)/D7 -> #DIV/0! | D7: =SUM(D5:D6) -> 0 | E7: =(F7-D7)/F7 -> #DIV/0! | F7: =SUM(F5:F6) -> 0 | G7: =G8 -> 0 | H7: =(I7-G7)/I7 -> #DIV/0! | I7: =SUM(I5:I6) -> 0 | J7: =(I7-K7)/K7 -> #DIV/0! | K7: =SUM(K5:K6) -> 0 | L7: =SUM(L5:L6) -> 0 | M7: =(N7-L7)/N7 -> #DIV/0! | N7: =SUM(N5:N6) -> 0 | O7: =(N7-P7)/P7 -> #DIV/0! | P7: =P5+P6 -> 0 | Q7: =B7+G7+L7 -> 0 | R7: =D7+I7+N7 -> 0 | S7: =F7+K7+P7 -> 0
A8: Aprile | B8: 0 | C8: =(D8-B8)/D8 -> #DIV/0! | D8: 0 | E8: =(D8-F8)/F8 -> #DIV/0! | F8: 0 | G8: 0 | H8: =(I8-G8)/I8 -> #DIV/0! | I8: 0 | J8: =(I8-K8)/K8 -> #DIV/0! | K8: 0 | M8: =(N8-L8)/N8 -> #DIV/0! | N8: 0 | O8: =(N8-P8)/P8 -> #DIV/0! | P8: 0 | Q8: =B8+G8+L8 -> 0 | R8: =D8+I8+N8 -> 0 | S8: =F8+K8+P8 -> 0
A9: PROGRESSIVO | B9: =SUM(B7:B8) -> 0 | C9: =(D9-B9)/D9 -> #DIV/0! | D9: =SUM(D7:D8) -> 0 | E9: =(F9-D9)/F9 -> #DIV/0! | F9: =SUM(F7:F8) -> 0 | G9: =SUM(G7:G8) -> 0 | H9: =(I9-G9)/I9 -> #DIV/0! | I9: =SUM(I7:I8) -> 0 | J9: =(I9-K9)/K9 -> #DIV/0! | K9: =SUM(K7:K8) -> 0 | L9: =SUM(L7:L8) -> 0 | M9: =(N9-L9)/N9 -> #DIV/0! | N9: =SUM(N7:N8) -> 0 | O9: =(N9-P9)/P9 -> #DIV/0! | P9: =SUM(P7:P8) -> 0 | Q9: =B9+G9+L9 -> 0 | R9: =D9+I9+N9 -> 0 | S9: =F9+K9+P9 -> 0
A10: Maggio | B10: 0 | C10: =(D10-B10)/D10 -> #DIV/0! | D10: 0 | E10: =(D10-F10)/F10 -> #DIV/0! | F10: 0 | G10: 0 | H10: =(I10-G10)/I10 -> #DIV/0! | I10: 0 | J10: =(I10-K10)/K10 -> #DIV/0! | K10: 0 | M10: =(N10-L10)/N10 -> #DIV/0! | N10: 0 | O10: =(N10-P10)/P10 -> #DIV/0! | P10: 0 | Q10: =B10+G10+L10 -> 0 | R10: =D10+I10+N10 -> 0 | S10: =F10+K10+P10 -> 0
A11: PROGRESSIVO | B11: =SUM(B9:B10) -> 0 | C11: =(D11-B11)/D11 -> #DIV/0! | D11: =SUM(D9:D10) -> 0 | E11: =(F11-D11)/F11 -> #DIV/0! | F11: =SUM(F9:F10) -> 0 | G11: =SUM(G9:G10) -> 0 | H11: =(I11-G11)/I11 -> #DIV/0! | I11: =SUM(I9:I10) -> 0 | J11: =(I11-K11)/K11 -> #DIV/0! | K11: =SUM(K9:K10) -> 0 | L11: =SUM(L9:L10) -> 0 | M11: =(N11-L11)/N11 -> #DIV/0! | N11: =SUM(N9:N10) -> 0 | O11: =(N11-P11)/P11 -> #DIV/0! | P11: =SUM(P9:P10) -> 0 | Q11: =B11+G11+L11 -> 0 | R11: =D11+I11+N11 -> 0 | S11: =F11+K11+P11 -> 0
A12: Giugno | B12: 0 | C12: =(D12-B12)/D12 -> #DIV/0! | D12: 0 | E12: =(D12-F12)/F12 -> #DIV/0! | F12: 0 | G12: 0 | H12: =(I12-G12)/I12 -> #DIV/0! | I12: 0 | J12: =(I12-K12)/K12 -> #DIV/0! | K12: 0 | M12: =(N12-L12)/N12 -> #DIV/0! | N12: 0 | O12: =(N12-P12)/P12 -> #DIV/0! | P12: 0 | Q12: =B12+G12+L12 -> 0 | R12: =D12+I12+N12 -> 0 | S12: =F12+K12+P12 -> 0
A13: PROGRESSIVO | B13: =SUM(B11:B12) -> 0 | C13: =(D13-B13)/D13 -> #DIV/0! | D13: =SUM(D11:D12) -> 0 | E13: =(F13-D13)/F13 -> #DIV/0! | F13: =SUM(F11:F12) -> 0 | G13: =SUM(G11:G12) -> 0 | H13: =(I13-G13)/I13 -> #DIV/0! | I13: =SUM(I11:I12) -> 0 | J13: =(I13-K13)/K13 -> #DIV/0! | K13: =SUM(K11:K12) -> 0 | L13: =SUM(L11:L12) -> 0 | M13: =(N13-L13)/N13 -> #DIV/0! | N13: =SUM(N11:N12) -> 0 | O13: =(N13-P13)/P13 -> #DIV/0! | P13: =SUM(P11:P12) -> 0 | Q13: =B13+G13+L13 -> 0 | R13: =D13+I13+N13 -> 0 | S13: =F13+K13+P13 -> 0
A14: Luglio | B14: 0 | C14: =(D14-B14)/D14 -> #DIV/0! | D14: 0 | E14: =(D14-F14)/F14 -> #DIV/0! | F14: 0 | G14: 0 | H14: =(I14-G14)/I14 -> #DIV/0! | I14: 0 | J14: =(I14-K14)/K14 -> #DIV/0! | K14: 0 | M14: =(N14-L14)/N14 -> #DIV/0! | N14: 0 | O14: =(N14-P14)/P14 -> #DIV/0! | P14: 0 | Q14: =B14+G14+L14 -> 0 | R14: =D14+I14+N14 -> 0 | S14: =F14+K14+P14 -> 0
A15: PROGRESSIVO | B15: =SUM(B13:B14) -> 0 | C15: =(D15-B15)/D15 -> #DIV/0! | D15: =SUM(D13:D14) -> 0 | E15: =(F15-D15)/F15 -> #DIV/0! | F15: =SUM(F13:F14) -> 0 | G15: =SUM(G13:G14) -> 0 | H15: =(I15-G15)/I15 -> #DIV/0! | I15: =SUM(I13:I14) -> 0 | J15: =(I15-K15)/K15 -> #DIV/0! | K15: =SUM(K13:K14) -> 0 | L15: =SUM(L13:L14) -> 0 | M15: =(N15-L15)/N15 -> #DIV/0! | N15: =SUM(N13:N14) -> 0 | O15: =(N15-P15)/P15 -> #DIV/0! | P15: =SUM(P13:P14) -> 0 | Q15: =B15+G15+L15 -> 0 | R15: =D15+I15+N15 -> 0 | S15: =F15+K15+P15 -> 0
A16: Agosto | B16: 0 | C16: =(D16-B16)/D16 -> #DIV/0! | D16: 0 | E16: =(D16-F16)/F16 -> #DIV/0! | F16: 0 | G16: 0 | H16: =(I16-G16)/I16 -> #DIV/0! | I16: 0 | J16: =(I16-K16)/K16 -> #DIV/0! | K16: 0 | M16: =(N16-L16)/N16 -> #DIV/0! | N16: 0 | O16: =(N16-P16)/P16 -> #DIV/0! | P16: 0 | Q16: =B16+G16+L16 -> 0 | R16: =D16+I16+N16 -> 0 | S16: =F16+K16+P16 -> 0
A17: PROGRESSIVO | B17: =SUM(B15:B16) -> 0 | C17: =(D17-B17)/D17 -> #DIV/0! | D17: =SUM(D15:D16) -> 0 | E17: =(F17-D17)/F17 -> #DIV/0! | F17: =SUM(F15:F16) -> 0 | G17: =SUM(G15:G16) -> 0 | H17: =(I17-G17)/I17 -> #DIV/0! | I17: =SUM(I15:I16) -> 0 | J17: =(I17-K17)/K17 -> #DIV/0! | K17: =SUM(K15:K16) -> 0 | L17: =SUM(L15:L16) -> 0 | M17: =(N17-L17)/N17 -> #DIV/0! | N17: =SUM(N15:N16) -> 0 | O17: =(N17-P17)/P17 -> #DIV/0! | P17: =SUM(P15:P16) -> 0 | Q17: =B17+G17+L17 -> 0 | R17: =D17+I17+N17 -> 0 | S17: =F17+K17+P17 -> 0
A18: Settembre | B18: 0 | C18: =(D18-B18)/D18 -> #DIV/0! | D18: 0 | E18: =(D18-F18)/F18 -> #DIV/0! | F18: 0 | G18: 0 | H18: =(I18-G18)/I18 -> #DIV/0! | I18: 0 | J18: =(I18-K18)/K18 -> #DIV/0! | K18: 0 | M18: =(N18-L18)/N18 -> #DIV/0! | N18: 0 | O18: =(N18-P18)/P18 -> #DIV/0! | P18: 0 | Q18: =B18+G18+L18 -> 0 | R18: =D18+I18+N18 -> 0 | S18: =F18+K18+P18 -> 0
A19: PROGRESSIVO | B19: =SUM(B17:B18) -> 0 | C19: =(D19-B19)/D19 -> #DIV/0! | D19: =SUM(D17:D18) -> 0 | E19: =(F19-D19)/F19 -> #DIV/0! | F19: =SUM(F17:F18) -> 0 | G19: =SUM(G17:G18) -> 0 | H19: =(I19-G19)/I19 -> #DIV/0! | I19: =SUM(I17:I18) -> 0 | J19: =(I19-K19)/K19 -> #DIV/0! | K19: =SUM(K17:K18) -> 0 | L19: =SUM(L17:L18) -> 0 | M19: =(N19-L19)/N19 -> #DIV/0! | N19: =SUM(N17:N18) -> 0 | O19: =(N19-P19)/P19 -> #DIV/0! | P19: =SUM(P17:P18) -> 0 | Q19: =B19+G19+L19 -> 0 | R19: =D19+I19+N19 -> 0 | S19: =F19+K19+P19 -> 0
A20: Ottobre | B20: 0 | C20: =(D20-B20)/D20 -> #DIV/0! | D20: 0 | E20: =(D20-F20)/F20 -> #DIV/0! | F20: 0 | G20: 0 | H20: =(I20-G20)/I20 -> #DIV/0! | I20: 0 | J20: =(I20-K20)/K20 -> #DIV/0! | K20: 0 | M20: =(N20-L20)/N20 -> #DIV/0! | N20: 0 | O20: =(N20-P20)/P20 -> #DIV/0! | P20: 0 | Q20: =B20+G20+L20 -> 0 | R20: =D20+I20+N20 -> 0 | S20: =F20+K20+P20 -> 0
A21: PROGRESSIVO | B21: =SUM(B19:B20) -> 0 | C21: =(D21-B21)/D21 -> #DIV/0! | D21: =SUM(D19:D20) -> 0 | E21: =(F21-D21)/F21 -> #DIV/0! | F21: =SUM(F19:F20) -> 0 | G21: =SUM(G19:G20) -> 0 | H21: =(I21-G21)/I21 -> #DIV/0! | I21: =SUM(I19:I20) -> 0 | J21: =(I21-K21)/K21 -> #DIV/0! | K21: =SUM(K19:K20) -> 0 | L21: =SUM(L19:L20) -> 0 | M21: =(N21-L21)/N21 -> #DIV/0! | N21: =SUM(N19:N20) -> 0 | O21: =(N21-P21)/P21 -> #DIV/0! | P21: =SUM(P19:P20) -> 0 | Q21: =B21+G21+L21 -> 0 | R21: =D21+I21+N21 -> 0 | S21: =F21+K21+P21 -> 0
A22: Novembre | B22: 0 | C22: =(D22-B22)/D22 -> #DIV/0! | D22: 0 | E22: =(D22-F22)/F22 -> #DIV/0! | F22: 0 | G22: 0 | H22: =(I22-G22)/I22 -> #DIV/0! | I22: 0 | J22: =(I22-K22)/K22 -> #DIV/0! | K22: 0 | M22: =(N22-L22)/N22 -> #DIV/0! | N22: 0 | O22: =(N22-P22)/P22 -> #DIV/0! | P22: 0 | Q22: =B22+G22+L22 -> 0 | R22: =D22+I22+N22 -> 0 | S22: =F22+K22+P22 -> 0
A23: PROGRESSIVO | B23: =SUM(B21:B22) -> 0 | C23: =(D23-B23)/D23 -> #DIV/0! | D23: =SUM(D21:D22) -> 0 | E23: =(F23-D23)/F23 -> #DIV/0! | F23: =SUM(F21:F22) -> 0 | G23: =SUM(G21:G22) -> 0 | H23: =(I23-G23)/I23 -> #DIV/0! | I23: =SUM(I21:I22) -> 0 | J23: =(I23-K23)/K23 -> #DIV/0! | K23: =SUM(K21:K22) -> 0 | L23: =SUM(L21:L22) -> 0 | M23: =(N23-L23)/N23 -> #DIV/0! | N23: =SUM(N21:N22) -> 0 | O23: =(N23-P23)/P23 -> #DIV/0! | P23: =SUM(P21:P22) -> 0 | Q23: =B23+G23+L23 -> 0 | R23: =D23+I23+N23 -> 0 | S23: =F23+K23+P23 -> 0
A24: Dicembre | B24: 0 | C24: =(D24-B24)/D24 -> #DIV/0! | D24: 0 | E24: =(D24-F24)/F24 -> #DIV/0! | F24: 0 | G24: 0 | H24: =(I24-G24)/I24 -> #DIV/0! | I24: 0 | J24: =(I24-K24)/K24 -> #DIV/0! | K24: 0 | M24: =(N24-L24)/N24 -> #DIV/0! | N24: 0 | O24: =(N24-P24)/P24 -> #DIV/0! | P24: 0 | Q24: =B24+G24+L24 -> 0 | R24: =D24+I24+N24 -> 0 | S24: =F24+K24+P24 -> 0
A25: TOTALI | B25: =B23+B24 -> 0 | C25: =(D25-B25)/D25 -> #DIV/0! | D25: =D23+D24 -> 0 | E25: =(D25-F25)/F25 -> #DIV/0! | F25: =F23+F24 -> 0 | G25: =G23+G24 -> 0 | H25: =(I25-G25)/I25 -> #DIV/0! | I25: =I23+I24 -> 0 | J25: =(I25-K25)/K25 -> #DIV/0! | K25: =K23+K24 -> 0 | L25: =L23+L24 -> 0 | M25: =(N25-L25)/N25 -> #DIV/0! | N25: =N23+N24 -> 0 | O25: =(N25-P25)/P25 -> #DIV/0! | P25: =P23+P24 -> 0 | Q25: =B25+G25+L25 -> 0 | R25: =D25+I25+N25 -> 0 | S25: =F25+K25+P25 -> 0

Sheet costi-ricavi totali
A1: RICAVI TOTALI | B1: 2024 | C1: 2025/2024 | D1: 2025 | E1: 2025/Bdg | F1: Budget | G1: Agg. 01/08/2025
A2: HOTEL | B2: ='Ricavi Gruppo x asset'!B25 -> 0 | C2: =(D2-B2)/B2 -> #DIV/0! | D2: ='Ricavi Gruppo x asset'!D25 -> 0 | E2: =(D2-F2)/D2 -> #DIV/0! | F2: ='Ricavi Gruppo x asset'!F25 -> 0
A3: RESIDENCE | B3: ='Ricavi Gruppo x asset'!G25 -> 0 | C3: =(D3-B3)/B3 -> #DIV/0! | D3: ='Ricavi Gruppo x asset'!I25 -> 0 | E3: =(D3-F3)/D3 -> #DIV/0! | F3: ='Ricavi Gruppo x asset'!K25 -> 0
A4: CVM | B4: ='Ricavi Gruppo x asset'!L25 -> 0 | C4: =(D4-B4)/B4 -> #DIV/0! | D4: ='Ricavi Gruppo x asset'!N25 -> 0 | E4: =(D4-F4)/D4 -> #DIV/0! | F4: ='Ricavi Gruppo x asset'!P25 -> 0
A5: TOTALI | B5: =SUM(B2:B4) -> 0 | C5: =(D5-B5)/B5 -> #DIV/0! | D5: =SUM(D2:D4) -> 0 | E5: =(D5-F5)/D5 -> #DIV/0! | F5: =SUM(F2:F4) -> 0
A8: COSTI TOTALI | B8: PERSONALE | G8: PRODUZIONE | L8: GESTIONE E FIN. | Q8: COMMERCIAL.
B9: 2024 | C9: 2025/2024 | D9: 2025 | E9: 2025/Bdg | F9: budget | G9: 2024 | H9: 2025/2024 | I9: 2025 | J9: 2025/Bdg | K9: Budget | L9: 2024 | M9: 2025/2024 | N9: 2025 | O9: 2025/Bdg | P9: Budget | Q9: 2024 | R9: 202/2024 | S9: 2025 | T9: 2025/Bdg | U9: Budget
A10: HOTEL | B10: ='Costi x asset'!B16 -> 0 | C10: =(D10-B10)/B10 -> #DIV/0! | D10: ='Costi x asset'!C16 -> 0 | E10: =(F10-D10)/D10 -> #DIV/0! | F10: ='Costi x asset'!D16 -> 0 | G10: ='Costi x asset'!E16 -> 0 | H10: =(I10-G10)/G10 -> #DIV/0! | I10: ='Costi x asset'!F16 -> 0 | J10: =(K10-I10)/I10 -> #DIV/0! | K10: ='Costi x asset'!G16 -> 0 | L10: ='Costi x asset'!H16 -> 0 | M10: =(N10-L10)/L10 -> #DIV/0! | N10: ='Costi x asset'!I16 -> 0 | O10: =(P10-N10)/N10 -> #DIV/0! | P10: ='Costi x asset'!J16 -> 0 | Q10: ='Costi x asset'!K16 -> 0 | R10: =(S10-Q10)/Q10 -> #DIV/0! | S10: ='Costi x asset'!L16 -> 0 | T10: =(U10-S10)/S10 -> #DIV/0! | U10: ='Costi x asset'!M16 -> 0
A11: RESIDENCE | B11: ='Costi x asset'!P16 -> 0 | C11: =(D11-B11)/B11 -> #DIV/0! | D11: ='Costi x asset'!Q16 -> 0 | E11: =(F11-D11)/D11 -> #DIV/0! | F11: ='Costi x asset'!R16 -> 0 | G11: ='Costi x asset'!S16 -> 0 | H11: =(I11-G11)/G11 -> #DIV/0! | I11: ='Costi x asset'!T16 -> 0 | J11: =(K11-I11)/I11 -> #DIV/0! | K11: ='Costi x asset'!U16 -> 0 | L11: ='Costi x asset'!V16 -> 0 | M11: =(N11-L11)/L11 -> #DIV/0! | N11: ='Costi x asset'!W16 -> 0 | O11: =(P11-N11)/N11 -> #DIV/0! | P11: ='Costi x asset'!X16 -> 0 | Q11: ='Costi x asset'!Y16 -> 0 | R11: =(S11-Q11)/Q11 -> #DIV/0! | S11: ='Costi x asset'!Z16 -> 0 | T11: =(U11-S11)/S11 -> #DIV/0! | U11: ='Costi x asset'!AA16 -> 0
A12: C.V.M. | B12: ='Costi x asset'!B34 -> 0 | C12: =(D12-B12)/B12 -> #DIV/0! | D12: ='Costi x asset'!C34 -> 0 | E12: =(F12-D12)/D12 -> #DIV/0! | F12: ='Costi x asset'!D34 -> 0 | G12: ='Costi x asset'!E34 -> 0 | H12: =(I12-G12)/G12 -> #DIV/0! | I12: ='Costi x asset'!F34 -> 0 | J12: =(K12-I12)/I12 -> #DIV/0! | K12: ='Costi x asset'!G34 -> 0 | L12: ='Costi x asset'!H34 -> 0 | M12: =(N12-L12)/L12 -> #DIV/0! | N12: ='Costi x asset'!I34 -> 0 | O12: =(P12-N12)/N12 -> #DIV/0! | P12: ='Costi x asset'!J34 -> 0 | Q12: ='Costi x asset'!K34 -> 0 | R12: =(S12-Q12)/Q12 -> #DIV/0! | S12: ='Costi x asset'!L34 -> 0 | T12: =(U12-S12)/S12 -> #DIV/0! | U12: ='Costi x asset'!M34 -> 0
A13: TOTALI | B13: =SUM(B10:B12) -> 0 | C13: =(D13-B13)/B13 -> #DIV/0! | D13: =SUM(D10:D12) -> 0 | E13: =(F13-D13)/D13 -> #DIV/0! | F13: =SUM(F10:F12) -> 0 | G13: =SUM(G10:G12) -> 0 | H13: =(I13-G13)/G13 -> #DIV/0! | I13: =SUM(I10:I12) -> 0 | J13: =(K13-I13)/I13 -> #DIV/0! | K13: =SUM(K10:K12) -> 0 | L13: =SUM(L10:L12) -> 0 | M13: =(N13-L13)/L13 -> #DIV/0! | N13: =SUM(N10:N12) -> 0 | O13: =(P13-N13)/N13 -> #DIV/0! | P13: =SUM(P10:P12) -> 0 | Q13: =SUM(Q10:Q12) -> 0 | R13: =(S13-Q13)/Q13 -> #DIV/0! | S13: =SUM(S10:S12) -> 0 | T13: =(U13-S13)/S13 -> #DIV/0! | U13: =SUM(U10:U12) -> 0
B15: 2024 | C15: 2025 | D15: Budget
A16: RICAVI TOTALI | B16: =B5 -> 0 | C16: =D5 -> 0 | D16: =F5 -> 0
A17: COSTI TOTALI | B17: =B13+G13+L13+Q13 -> 0 | C17: =D13+I13+N13+S13 -> 0 | D17: =F13+K13+P13+U13 -> 0
B18: =B16-B17 -> 0 | C18: =C16-C17 -> 0 | D18: =D16-D17 -> 0
B20: 2024 | C20: 2025 | D20: Budget
A21: RICAVI TOTALI | B21: =B10 -> 0 | C21: =D10 -> 0 | D21: =F10 -> 0
A22: COSTI PROD. | B22: =G13 -> 0 | C22: =I13 -> 0 | D22: =K13 -> 0
A23: PRIMO MARGINE | B23: =B21-B22 -> 0 | C23: =C21-C22 -> 0 | D23: =D21-D22 -> 0

Sheet Ricavi Gruppo x asset
B1: HOTEL | G1: RESIDENCE | L1: C.V.M. | Q1: TOTALI
A2: RICAVI | B2: 2024 | C2: 2025/2024 | D2: 2025 | E2: 2025/Bdg | F2: Budget | G2: 2024 | H2: 2025/2024 | I2: 2025 | J2: 2025/Bdg | K2: Budget | L2: 2024 | M2: 2025/2024 | N2: 2025 | O2: 2025/Bdg | P2: Budget
A3: Gennaio | C3: =(D3-B3)/D3 -> #DIV/0! | D3: ='Ricavi Hotel per asset'!R3 -> 0 | E3: =(D3-F3)/F3 -> #DIV/0! | F3: ='Ricavi Hotel per asset'!S3 -> 0 | G3: 0 | H3: =(I3-G3)/I3 -> #DIV/0! | I3: 0 | J3: =(I3-K3)/K3 -> #DIV/0! | K3: 0 | L3: 0 | M3: =(N3-L3)/N3 -> #DIV/0! | N3: 0 | O3: =(N3-P3)/P3 -> #DIV/0! | P3: 0
A4: Febbraio | C4: =(D4-B4)/D4 -> #DIV/0! | D4: ='Ricavi Hotel per asset'!R4 -> 0 | E4: =(D4-F4)/F4 -> #DIV/0! | F4: ='Ricavi Hotel per asset'!S4 -> 0 | G4: 0 | H4: =(I4-G4)/I4 -> #DIV/0! | I4: 0 | J4: =(I4-K4)/K4 -> #DIV/0! | K4: 0 | L4: 0 | M4: =(N4-L4)/N4 -> #DIV/0! | N4: 0 | O4: =(N4-P4)/P4 -> #DIV/0! | P4: 0
A5: PROGRESSIVO | B5: ='Ricavi Hotel per asset'!Q5 -> 0 | C5: =(D5-B5)/D5 -> #DIV/0! | D5: ='Ricavi Hotel per asset'!R5 -> 0 | E5: =(F5-D5)/F5 -> #DIV/0! | F5: ='Ricavi Hotel per asset'!S5 -> 0 | G5: =SUM(G3:G4) -> 0 | H5: =(I5-G5)/I5 -> #DIV/0! | I5: =SUM(I3:I4) -> 0 | J5: =(I5-K5)/K5 -> #DIV/0! | K5: =SUM(K3:K4) -> 0 | L5: =SUM(L3:L4) -> 0 | M5: =(N5-L5)/N5 -> #DIV/0! | N5: =SUM(N3:N4) -> 0 | O5: =(N5-P5)/P5 -> #DIV/0! | P5: =SUM(P3:P4) -> 0
A6: Marzo | C6: =(D6-B6)/D6 -> #DIV/0! | D6: ='Ricavi Hotel per asset'!R6 -> 0 | E6: =(D6-F6)/F6 -> #DIV/0! | F6: ='Ricavi Hotel per asset'!S6 -> 0 | G6: 0 | H6: =(I6-G6)/I6 -> #DIV/0! | I6: 0 | J6: =(I6-K6)/K6 -> #DIV/0! | K6: 0 | L6: 0 | M6: =(N6-L6)/N6 -> #DIV/0! | N6: 0 | O6: =(N6-P6)/P6 -> #DIV/0! | P6: 0
A7: PROGRESSIVO | B7: ='Ricavi Hotel per asset'!Q7 -> 0 | C7: =(D7-B7)/D7 -> #DIV/0! | D7: ='Ricavi Hotel per asset'!R7 -> 0 | E7: =(F7-D7)/F7 -> #DIV/0! | F7: ='Ricavi Hotel per asset'!S7 -> 0 | G7: =SUM(G5:G6) -> 0 | H7: =(I7-G7)/I7 -> #DIV/0! | I7: =SUM(I5:I6) -> 0 | J7: =(I7-K7)/K7 -> #DIV/0! | K7: =SUM(K5:K6) -> 0 | L7: =SUM(L5:L6) -> 0 | M7: =(N7-L7)/N7 -> #DIV/0! | N7: =SUM(N5:N6) -> 0 | O7: =(N7-P7)/P7 -> #DIV/0! | P7: =SUM(P5:P6) -> 0
A8: Aprile | C8: =(D8-B8)/D8 -> #DIV/0! | D8: ='Ricavi Hotel per asset'!R8 -> 0 | E8: =(D8-F8)/F8 -> #DIV/0! | F8: ='Ricavi Hotel per asset'!S8 -> 0 | G8: 0 | H8: =(I8-G8)/I8 -> #DIV/0! | I8: 0 | J8: =(I8-K8)/K8 -> #DIV/0! | K8: 0 | L8: 0 | M8: =(N8-L8)/N8 -> #DIV/0! | N8: 0 | O8: =(N8-P8)/P8 -> #DIV/0! | P8: 0
A9: PROGRESSIVO | B9: ='Ricavi Hotel per asset'!Q9 -> 0 | C9: =(D9-B9)/D9 -> #DIV/0! | D9: ='Ricavi Hotel per asset'!R9 -> 0 | E9: =(F9-D9)/F9 -> #DIV/0! | F9: ='Ricavi Hotel per asset'!S9 -> 0 | G9: =SUM(G7:G8) -> 0 | H9: =(I9-G9)/I9 -> #DIV/0! | I9: =SUM(I7:I8) -> 0 | J9: =(I9-K9)/K9 -> #DIV/0! | K9: =SUM(K7:K8) -> 0 | L9: =SUM(L7:L8) -> 0 | M9: =(N9-L9)/N9 -> #DIV/0! | N9: =SUM(N7:N8) -> 0 | O9: =(N9-P9)/P9 -> #DIV/0! | P9: =SUM(P7:P8) -> 0
A10: Maggio | B10: ='Ricavi Hotel per asset'!Q10 -> 0 | C10: =(D10-B10)/D10 -> #DIV/0! | D10: ='Ricavi Hotel per asset'!R10 -> 0 | E10: =(D10-F10)/F10 -> #DIV/0! | F10: ='Ricavi Hotel per asset'!S10 -> 0 | G10: 0 | H10: =(I10-G10)/I10 -> #DIV/0! | I10: 0 | J10: =(I10-K10)/K10 -> #DIV/0! | K10: 0 | L10: 0 | M10: =(N10-L10)/N10 -> #DIV/0! | N10: 0 | O10: =(N10-P10)/P10 -> #DIV/0! | P10: 0
A11: PROGRESSIVO | B11: ='Ricavi Hotel per asset'!Q11 -> 0 | C11: =(D11-B11)/D11 -> #DIV/0! | D11: ='Ricavi Hotel per asset'!R11 -> 0 | E11: =(F11-D11)/F11 -> #DIV/0! | F11: ='Ricavi Hotel per asset'!S11 -> 0 | G11: =SUM(G9:G10) -> 0 | H11: =(I11-G11)/I11 -> #DIV/0! | I11: =SUM(I9:I10) -> 0 | J11: =(I11-K11)/K11 -> #DIV/0! | K11: =SUM(K9:K10) -> 0 | L11: =SUM(L9:L10) -> 0 | M11: =(N11-L11)/N11 -> #DIV/0! | N11: =SUM(N9:N10) -> 0 | O11: =(N11-P11)/P11 -> #DIV/0! | P11: =SUM(P9:P10) -> 0
A12: Giugno | B12: ='Ricavi Hotel per asset'!Q12 -> 0 | C12: =(D12-B12)/D12 -> #DIV/0! | D12: ='Ricavi Hotel per asset'!R12 -> 0 | E12: =(D12-F12)/F12 -> #DIV/0! | F12: ='Ricavi Hotel per asset'!S12 -> 0 | G12: 0 | H12: =(I12-G12)/I12 -> #DIV/0! | I12: 0 | J12: =(I12-K12)/K12 -> #DIV/0! | K12: 0 | L12: 0 | M12: =(N12-L12)/N12 -> #DIV/0! | N12: 0 | O12: =(N12-P12)/P12 -> #DIV/0! | P12: 0
A13: PROGRESSIVO | B13: ='Ricavi Hotel per asset'!Q13 -> 0 | C13: =(D13-B13)/D13 -> #DIV/0! | D13: ='Ricavi Hotel per asset'!R13 -> 0 | E13: =(F13-D13)/F13 -> #DIV/0! | F13: ='Ricavi Hotel per asset'!S13 -> 0 | G13: =SUM(G11:G12) -> 0 | H13: =(I13-G13)/I13 -> #DIV/0! | I13: =SUM(I11:I12) -> 0 | J13: =(I13-K13)/K13 -> #DIV/0! | K13: =SUM(K11:K12) -> 0 | L13: =SUM(L11:L12) -> 0 | M13: =(N13-L13)/N13 -> #DIV/0! | N13: =SUM(N11:N12) -> 0 | O13: =(N13-P13)/P13 -> #DIV/0! | P13: =SUM(P11:P12) -> 0
A14: Luglio | B14: ='Ricavi Hotel per asset'!Q14 -> 0 | C14: =(D14-B14)/D14 -> #DIV/0! | D14: ='Ricavi Hotel per asset'!R14 -> 0 | E14: =(D14-F14)/F14 -> #DIV/0! | F14: ='Ricavi Hotel per asset'!S14 -> 0 | G14: 0 | H14: =(I14-G14)/I14 -> #DIV/0! | I14: 0 | J14: =(I14-K14)/K14 -> #DIV/0! | K14: 0 | L14: 0 | M14: =(N14-L14)/N14 -> #DIV/0! | N14: 0 | O14: =(N14-P14)/P14 -> #DIV/0! | P14: 0
A15: PROGRESSIVO | B15: ='Ricavi Hotel per asset'!Q15 -> 0 | C15: =(D15-B15)/D15 -> #DIV/0! | D15: ='Ricavi Hotel per asset'!R15 -> 0 | E15: =(F15-D15)/F15 -> #DIV/0! | F15: ='Ricavi Hotel per asset'!S15 -> 0 | G15: =SUM(G13:G14) -> 0 | H15: =(I15-G15)/I15 -> #DIV/0! | I15: =SUM(I13:I14) -> 0 | J15: =(I15-K15)/K15 -> #DIV/0! | K15: =SUM(K13:K14) -> 0 | L15: =SUM(L13:L14) -> 0 | M15: =(N15-L15)/N15 -> #DIV/0! | N15: =SUM(N13:N14) -> 0 | O15: =(N15-P15)/P15 -> #DIV/0! | P15: =SUM(P13:P14) -> 0
A16: Agosto | B16: ='Ricavi Hotel per asset'!Q16 -> 0 | C16: =(D16-B16)/D16 -> #DIV/0! | D16: ='Ricavi Hotel per asset'!R16 -> 0 | E16: =(D16-F16)/F16 -> #DIV/0! | F16: ='Ricavi Hotel per asset'!S16 -> 0 | G16: 0 | H16: =(I16-G16)/I16 -> #DIV/0! | I16: 0 | J16: =(I16-K16)/K16 -> #DIV/0! | K16: 0 | L16: 0 | M16: =(N16-L16)/N16 -> #DIV/0! | N16: 0 | O16: =(N16-P16)/P16 -> #DIV/0! | P16: 0
A17: PROGRESSIVO | B17: ='Ricavi Hotel per asset'!Q17 -> 0 | C17: =(D17-B17)/D17 -> #DIV/0! | D17: ='Ricavi Hotel per asset'!R17 -> 0 | E17: =(F17-D17)/F17 -> #DIV/0! | F17: ='Ricavi Hotel per asset'!S17 -> 0 | G17: =SUM(G15:G16) -> 0 | H17: =(I17-G17)/I17 -> #DIV/0! | I17: =SUM(I15:I16) -> 0 | J17: =(I17-K17)/K17 -> #DIV/0! | K17: =SUM(K15:K16) -> 0 | L17: =SUM(L15:L16) -> 0 | M17: =(N17-L17)/N17 -> #DIV/0! | N17: =SUM(N15:N16) -> 0 | O17: =(N17-P17)/P17 -> #DIV/0! | P17: =SUM(P15:P16) -> 0
A18: Settembre | B18: ='Ricavi Hotel per asset'!Q18 -> 0 | C18: =(D18-B18)/D18 -> #DIV/0! | D18: ='Ricavi Hotel per asset'!R18 -> 0 | E18: =(D18-F18)/F18 -> #DIV/0! | F18: ='Ricavi Hotel per asset'!S18 -> 0 | G18: 0 | H18: =(I18-G18)/I18 -> #DIV/0! | I18: 0 | J18: =(I18-K18)/K18 -> #DIV/0! | K18: 0 | L18: 0 | M18: =(N18-L18)/N18 -> #DIV/0! | N18: 0 | O18: =(N18-P18)/P18 -> #DIV/0! | P18: 0
A19: PROGRESSIVO | B19: ='Ricavi Hotel per asset'!Q19 -> 0 | C19: =(D19-B19)/D19 -> #DIV/0! | D19: ='Ricavi Hotel per asset'!R19 -> 0 | E19: =(F19-D19)/F19 -> #DIV/0! | F19: ='Ricavi Hotel per asset'!S19 -> 0 | G19: =SUM(G17:G18) -> 0 | H19: =(I19-G19)/I19 -> #DIV/0! | I19: =SUM(I17:I18) -> 0 | J19: =(I19-K19)/K19 -> #DIV/0! | K19: =SUM(K17:K18) -> 0 | L19: =SUM(L17:L18) -> 0 | M19: =(N19-L19)/N19 -> #DIV/0! | N19: =SUM(N17:N18) -> 0 | O19: =(N19-P19)/P19 -> #DIV/0! | P19: =SUM(P17:P18) -> 0
A20: Ottobre | B20: ='Ricavi Hotel per asset'!Q20 -> 0 | C20: =(D20-B20)/D20 -> #DIV/0! | D20: ='Ricavi Hotel per asset'!R20 -> 0 | E20: =(D20-F20)/F20 -> #DIV/0! | F20: ='Ricavi Hotel per asset'!S20 -> 0 | G20: 0 | H20: =(I20-G20)/I20 -> #DIV/0! | I20: 0 | J20: =(I20-K20)/K20 -> #DIV/0! | K20: 0 | L20: 0 | M20: =(N20-L20)/N20 -> #DIV/0! | N20: 0 | O20: =(N20-P20)/P20 -> #DIV/0! | P20: 0
A21: PROGRESSIVO | B21: ='Ricavi Hotel per asset'!Q21 -> 0 | C21: =(D21-B21)/D21 -> #DIV/0! | D21: ='Ricavi Hotel per asset'!R21 -> 0 | E21: =(F21-D21)/F21 -> #DIV/0! | F21: ='Ricavi Hotel per asset'!S21 -> 0 | G21: =SUM(G19:G20) -> 0 | H21: =(I21-G21)/I21 -> #DIV/0! | I21: =SUM(I19:I20) -> 0 | J21: =(I21-K21)/K21 -> #DIV/0! | K21: =SUM(K19:K20) -> 0 | L21: =SUM(L19:L20) -> 0 | M21: =(N21-L21)/N21 -> #DIV/0! | N21: =SUM(N19:N20) -> 0 | O21: =(N21-P21)/P21 -> #DIV/0! | P21: =SUM(P19:P20) -> 0
A22: Novembre | B22: ='Ricavi Hotel per asset'!Q22 -> 0 | C22: =(D22-B22)/D22 -> #DIV/0! | D22: ='Ricavi Hotel per asset'!R22 -> 0 | E22: =(D22-F22)/F22 -> #DIV/0! | F22: ='Ricavi Hotel per asset'!S22 -> 0 | G22: 0 | H22: =(I22-G22)/I22 -> #DIV/0! | I22: 0 | J22: =(I22-K22)/K22 -> #DIV/0! | K22: 0 | L22: 0 | M22: =(N22-L22)/N22 -> #DIV/0! | N22: 0 | O22: =(N22-P22)/P22 -> #DIV/0! | P22: 0
A23: PROGRESSIVO | B23: ='Ricavi Hotel per asset'!Q23 -> 0 | C23: =(D23-B23)/D23 -> #DIV/0! | D23: ='Ricavi Hotel per asset'!R23 -> 0 | E23: =(F23-D23)/F23 -> #DIV/0! | F23: ='Ricavi Hotel per asset'!S23 -> 0 | G23: =SUM(G21:G22) -> 0 | H23: =(I23-G23)/I23 -> #DIV/0! | I23: =SUM(I21:I22) -> 0 | J23: =(I23-K23)/K23 -> #DIV/0! | K23: =SUM(K21:K22) -> 0 | L23: =SUM(L21:L22) -> 0 | M23: =(N23-L23)/N23 -> #DIV/0! | N23: =SUM(N21:N22) -> 0 | O23: =(N23-P23)/P23 -> #DIV/0! | P23: =SUM(P21:P22) -> 0
A24: Dicembre | B24: ='Ricavi Hotel per asset'!Q24 -> 0 | C24: =(D24-B24)/D24 -> #DIV/0! | D24: ='Ricavi Hotel per asset'!R24 -> 0 | E24: =(D24-F24)/F24 -> #DIV/0! | F24: ='Ricavi Hotel per asset'!S24 -> 0 | G24: 0 | H24: =(I24-G24)/I24 -> #DIV/0! | I24: 0 | J24: =(I24-K24)/K24 -> #DIV/0! | K24: 0 | L24: 0 | M24: =(N24-L24)/N24 -> #DIV/0! | N24: 0 | O24: =(N24-P24)/P24 -> #DIV/0! | P24: 0
A25: TOTALI | B25: =B23+B24 -> 0 | C25: =(D25-B25)/D25 -> #DIV/0! | D25: =D23+D24 -> 0 | E25: =(D25-F25)/F25 -> #DIV/0! | F25: =F23+F24 -> 0 | G25: =G23+G24 -> 0 | H25: =(I25-G25)/I25 -> #DIV/0! | I25: =I23+I24 -> 0 | J25: =(I25-K25)/K25 -> #DIV/0! | K25: =K23+K24 -> 0 | L25: =L23+L24 -> 0 | M25: =(N25-L25)/N25 -> #DIV/0! | N25: =N23+N24 -> 0 | O25: =(N25-P25)/P25 -> #DIV/0! | P25: =P23+P24 -> 0

Sheet incidenza costi-ricavi
B1: 2024 | G1: 2025 | L1: Budget | Q1: *** | S1: 2024 | X1: 2025 | AC1: Budget
A2: HOTEL | B2: Ricavi | C2: Costi (%) | G2: Ricavi | H2: Costi (%) | L2: Ricavi | M2: Costi (%) | R2: RESIDENCE | S2: Ricavi | T2: Costi (%) | X2: Ricavi | Y2: Costi (%) | AC2: Ricavi | AD2: Costi (%)
B3: € | C3: Personale | D3: Produzione | E3: Gest. e Fin. | F3: Commerciale | G3: € | H3: Personale | I3: Produzione | J3: Gest. e Fin. | K3: Commerciale | L3: € | M3: Personale | N3: Produzione | O3: Gest. e Fin. | P3: Commerciale | S3: € | T3: Personale | U3: Produzione | V3: Gest. e Fin. | W3: Commerciale | X3: € | Y3: Personale | Z3: Produzione | AA3: Gest. e Fin. | AB3: Commerciale | AC3: € | AD3: Personale | AE3: Produzione | AF3: Gest. e Fin. | AG3: Commerciale
A4: Gennaio | B4: ='Ricavi Gruppo x asset'!B3 | C4: ='Costi x asset'!B4/'incidenza costi-ricavi'!B4 -> #DIV/0! | D4: ='Costi x asset'!E4/'incidenza costi-ricavi'!B4 -> #DIV/0! | E4: ='Costi x asset'!H4/B4 -> #DIV/0! | F4: ='Costi x asset'!K4/B4 -> #DIV/0! | G4: ='Ricavi Gruppo x asset'!D3 -> 0 | H4: ='Costi x asset'!C4/'incidenza costi-ricavi'!G4 -> #DIV/0! | I4: ='Costi x asset'!F4/'incidenza costi-ricavi'!G4 -> #DIV/0! | J4: ='Costi x asset'!I4/'incidenza costi-ricavi'!G4 -> #DIV/0! | K4: ='Costi x asset'!L4/'incidenza costi-ricavi'!G4 -> #DIV/0! | L4: ='Ricavi Gruppo x asset'!F3 -> 0 | M4: ='Costi x asset'!D4/'incidenza costi-ricavi'!L4 -> #DIV/0! | N4: ='Costi x asset'!G4/'incidenza costi-ricavi'!L4 -> #DIV/0! | O4: ='Costi x asset'!J4/'incidenza costi-ricavi'!L4 -> #DIV/0! | P4: ='Costi x asset'!M4/'incidenza costi-ricavi'!L4 -> #DIV/0! | R4: Gennaio | S4: ='Ricavi Gruppo x asset'!#REF! -> #ERROR! | T4: ='Costi x asset'!B40/S4 -> #ERROR! | U4: ='Costi x asset'!E40/S4 -> #ERROR! | V4: ='Costi x asset'!H40/S4 -> #ERROR! | W4: ='Costi x asset'!K40/S4 -> #ERROR! | X4: ='Ricavi Gruppo x asset'!#REF! -> #ERROR! | Y4: ='Costi x asset'!C40/X4 -> #ERROR! | Z4: ='Costi x asset'!F40/X4 -> #ERROR! | AA4: ='Costi x asset'!I40/X4 -> #ERROR! | AB4: ='Costi x asset'!L40/X4 -> #ERROR! | AC4: ='Ricavi Gruppo x asset'!#REF! -> #ERROR! | AD4: ='Costi x asset'!D40/AC4 -> #ERROR! | AE4: ='Costi x asset'!G40/AC4 -> #ERROR! | AF4: ='Costi x asset'!J40/AC4 -> #ERROR! | AG4: ='Costi x asset'!M40/AC4 -> #ERROR!
A5: Febbraio | B5: ='Ricavi Gruppo x asset'!B4 | C5: ='Costi x asset'!B5/'incidenza costi-ricavi'!B5 -> #DIV/0! | D5: ='Costi x asset'!E5/'incidenza costi-ricavi'!B5 -> #DIV/0! | E5: ='Costi x asset'!H5/B5 -> #DIV/0! | F5: ='Costi x asset'!K5/B5 -> #DIV/0! | G5: ='Ricavi Gruppo x asset'!D4 -> 0 | H5: ='Costi x asset'!C5/'incidenza costi-ricavi'!G5 -> #DIV/0! | I5: ='Costi x asset'!F5/'incidenza costi-ricavi'!G5 -> #DIV/0! | J5: ='Costi x asset'!I5/'incidenza costi-ricavi'!G5 -> #DIV/0! | K5: ='Costi x asset'!L5/'incidenza costi-ricavi'!G5 -> #DIV/0! | L5: ='Ricavi Gruppo x asset'!F4 -> 0 | M5: ='Costi x asset'!D5/'incidenza costi-ricavi'!L5 -> #DIV/0! | N5: ='Costi x asset'!G5/'incidenza costi-ricavi'!L5 -> #DIV/0! | O5: ='Costi x asset'!J5/'incidenza costi-ricavi'!L5 -> #DIV/0! | P5: ='Costi x asset'!M5/'incidenza costi-ricavi'!L5 -> #DIV/0! | R5: Febbraio | S5: ='Ricavi Gruppo x asset'!#REF! -> #ERROR! | T5: ='Costi x asset'!B41/S5 -> #ERROR! | U5: ='Costi x asset'!E41/S5 -> #ERROR! | V5: ='Costi x asset'!H41/S5 -> #ERROR! | W5: ='Costi x asset'!K41/S5 -> #ERROR! | X5: ='Ricavi Gruppo x asset'!#REF! -> #ERROR! | Y5: ='Costi x asset'!C41/X5 -> #ERROR! | Z5: ='Costi x asset'!F41/X5 -> #ERROR! | AA5: ='Costi x asset'!I41/X5 -> #ERROR! | AB5: ='Costi x asset'!L41/X5 -> #ERROR! | AC5: ='Ricavi Gruppo x asset'!#REF! -> #ERROR! | AD5: ='Costi x asset'!D41/AC5 -> #ERROR! | AE5: ='Costi x asset'!G41/AC5 -> #ERROR! | AF5: ='Costi x asset'!J41/AC5 -> #ERROR! | AG5: ='Costi x asset'!M41/AC5 -> #ERROR!
A6: Marzo | B6: ='Ricavi Gruppo x asset'!B6 | C6: ='Costi x asset'!B6/'incidenza costi-ricavi'!B6 -> #DIV/0! | D6: ='Costi x asset'!E6/'incidenza costi-ricavi'!B6 -> #DIV/0! | E6: ='Costi x asset'!H6/B6 -> #DIV/0! | F6: ='Costi x asset'!K6/B6 -> #DIV/0! | G6: ='Ricavi Gruppo x asset'!D6 -> 0 | H6: ='Costi x asset'!C6/'incidenza costi-ricavi'!G6 -> #DIV/0! | I6: ='Costi x asset'!F6/'incidenza costi-ricavi'!G6 -> #DIV/0! | J6: ='Costi x asset'!I6/'incidenza costi-ricavi'!G6 -> #DIV/0! | K6: ='Costi x asset'!L6/'incidenza costi-ricavi'!G6 -> #DIV/0! | L6: ='Ricavi Gruppo x asset'!F6 -> 0 | M6: ='Costi x asset'!D6/'incidenza costi-ricavi'!L6 -> #DIV/0! | N6: ='Costi x asset'!G6/'incidenza costi-ricavi'!L6 -> #DIV/0! | O6: ='Costi x asset'!J6/'incidenza costi-ricavi'!L6 -> #DIV/0! | P6: ='Costi x asset'!M6/'incidenza costi-ricavi'!L6 -> #DIV/0! | R6: Marzo | S6: ='Ricavi Gruppo x asset'!#REF! -> #ERROR! | T6: ='Costi x asset'!B42/S6 -> #ERROR! | U6: ='Costi x asset'!E42/S6 -> #ERROR! | V6: ='Costi x asset'!H42/S6 -> #ERROR! | W6: ='Costi x asset'!K42/S6 -> #ERROR! | X6: ='Ricavi Gruppo x asset'!#REF! -> #ERROR! | Y6: ='Costi x asset'!C42/X6 -> #ERROR! | Z6: ='Costi x asset'!F42/X6 -> #ERROR! | AA6: ='Costi x asset'!I42/X6 -> #ERROR! | AB6: ='Costi x asset'!L42/X6 -> #ERROR! | AC6: ='Ricavi Gruppo x asset'!#REF! -> #ERROR! | AD6: ='Costi x asset'!D42/AC6 -> #ERROR! | AE6: ='Costi x asset'!G42/AC6 -> #ERROR! | AF6: ='Costi x asset'!J42/AC6 -> #ERROR! | AG6: ='Costi x asset'!M42/AC6 -> #ERROR!
A7: Aprile | B7: ='Ricavi Gruppo x asset'!B8 | C7: ='Costi x asset'!B7/'incidenza costi-ricavi'!B7 -> #DIV/0! | D7: ='Costi x asset'!E7/'incidenza costi-ricavi'!B7 -> #DIV/0! | E7: ='Costi x asset'!H7/B7 -> #DIV/0! | F7: ='Costi x asset'!K7/B7 -> #DIV/0! | G7: ='Ricavi Gruppo x asset'!D8 -> 0 | H7: ='Costi x asset'!C7/'incidenza costi-ricavi'!G7 -> #DIV/0! | I7: ='Costi x asset'!F7/'incidenza costi-ricavi'!G7 -> #DIV/0! | J7: ='Costi x asset'!I7/'incidenza costi-ricavi'!G7 -> #DIV/0! | K7: ='Costi x asset'!L7/'incidenza costi-ricavi'!G7 -> #DIV/0! | L7: ='Ricavi Gruppo x asset'!F8 -> 0 | M7: ='Costi x asset'!D7/'incidenza costi-ricavi'!L7 -> #DIV/0! | N7: ='Costi x asset'!G7/'incidenza costi-ricavi'!L7 -> #DIV/0! | O7: ='Costi x asset'!J7/'incidenza costi-ricavi'!L7 -> #DIV/0! | P7: ='Costi x asset'!M7/'incidenza costi-ricavi'!L7 -> #DIV/0! | R7: Aprile | S7: ='Ricavi Gruppo x asset'!#REF! -> #ERROR! | T7: ='Costi x asset'!B43/S7 -> #ERROR! | U7: ='Costi x asset'!E43/S7 -> #ERROR! | V7: ='Costi x asset'!H43/S7 -> #ERROR! | W7: ='Costi x asset'!K43/S7 -> #ERROR! | X7: ='Ricavi Gruppo x asset'!#REF! -> #ERROR! | Y7: ='Costi x asset'!C43/X7 -> #ERROR! | Z7: ='Costi x asset'!F43/X7 -> #ERROR! | AA7: ='Costi x asset'!I43/X7 -> #ERROR! | AB7: ='Costi x asset'!L43/X7 -> #ERROR! | AC7: ='Ricavi Gruppo x asset'!#REF! -> #ERROR! | AD7: ='Costi x asset'!D43/AC7 -> #ERROR! | AE7: ='Costi x asset'!G43/AC7 -> #ERROR! | AF7: ='Costi x asset'!J43/AC7 -> #ERROR! | AG7: ='Costi x asset'!M43/AC7 -> #ERROR!
A8: Maggio | B8: ='Ricavi Gruppo x asset'!B10 -> 0 | C8: ='Costi x asset'!B8/'incidenza costi-ricavi'!B8 -> #DIV/0! | D8: ='Costi x asset'!E8/'incidenza costi-ricavi'!B8 -> #DIV/0! | E8: ='Costi x asset'!H8/B8 -> #DIV/0! | F8: ='Costi x asset'!K8/B8 -> #DIV/0! | G8: ='Ricavi Gruppo x asset'!D10 -> 0 | H8: ='Costi x asset'!C8/'incidenza costi-ricavi'!G8 -> #DIV/0! | I8: ='Costi x asset'!F8/'incidenza costi-ricavi'!G8 -> #DIV/0! | J8: ='Costi x asset'!I8/'incidenza costi-ricavi'!G8 -> #DIV/0! | K8: ='Costi x asset'!L8/'incidenza costi-ricavi'!G8 -> #DIV/0! | L8: ='Ricavi Gruppo x asset'!F10 -> 0 | M8: ='Costi x asset'!D8/'incidenza costi-ricavi'!L8 -> #DIV/0! | N8: ='Costi x asset'!G8/'incidenza costi-ricavi'!L8 -> #DIV/0! | O8: ='Costi x asset'!J8/'incidenza costi-ricavi'!L8 -> #DIV/0! | P8: ='Costi x asset'!M8/'incidenza costi-ricavi'!L8 -> #DIV/0! | R8: Maggio | S8: ='Ricavi Gruppo x asset'!#REF! -> #ERROR! | T8: ='Costi x asset'!B44/S8 -> #ERROR! | U8: ='Costi x asset'!E44/S8 -> #ERROR! | V8: ='Costi x asset'!H44/S8 -> #ERROR! | W8: ='Costi x asset'!K44/S8 -> #ERROR! | X8: ='Ricavi Gruppo x asset'!#REF! -> #ERROR! | Y8: ='Costi x asset'!C44/X8 -> #ERROR! | Z8: ='Costi x asset'!F44/X8 -> #ERROR! | AA8: ='Costi x asset'!I44/X8 -> #ERROR! | AB8: ='Costi x asset'!L44/X8 -> #ERROR! | AC8: ='Ricavi Gruppo x asset'!#REF! -> #ERROR! | AD8: ='Costi x asset'!D44/AC8 -> #ERROR! | AE8: ='Costi x asset'!G44/AC8 -> #ERROR! | AF8: ='Costi x asset'!J44/AC8 -> #ERROR! | AG8: ='Costi x asset'!M44/AC8 -> #ERROR!
A9: Giugno | B9: ='Ricavi Gruppo x asset'!B12 -> 0 | C9: ='Costi x asset'!B9/'incidenza costi-ricavi'!B9 -> #DIV/0! | D9: ='Costi x asset'!E9/'incidenza costi-ricavi'!B9 -> #DIV/0! | E9: ='Costi x asset'!H9/B9 -> #DIV/0! | F9: ='Costi x asset'!K9/B9 -> #DIV/0! | G9: ='Ricavi Gruppo x asset'!D12 -> 0 | H9: ='Costi x asset'!C9/'incidenza costi-ricavi'!G9 -> #DIV/0! | I9: ='Costi x asset'!F9/'incidenza costi-ricavi'!G9 -> #DIV/0! | J9: ='Costi x asset'!I9/'incidenza costi-ricavi'!G9 -> #DIV/0! | K9: ='Costi x asset'!L9/'incidenza costi-ricavi'!G9 -> #DIV/0! | L9: ='Ricavi Gruppo x asset'!F12 -> 0 | M9: ='Costi x asset'!D9/'incidenza costi-ricavi'!L9 -> #DIV/0! | N9: ='Costi x asset'!G9/'incidenza costi-ricavi'!L9 -> #DIV/0! | O9: ='Costi x asset'!J9/'incidenza costi-ricavi'!L9 -> #DIV/0! | P9: ='Costi x asset'!M9/'incidenza costi-ricavi'!L9 -> #DIV/0! | R9: Giugno | S9: ='Ricavi Gruppo x asset'!#REF! -> #ERROR! | T9: ='Costi x asset'!B45/S9 -> #ERROR! | U9: ='Costi x asset'!E45/S9 -> #ERROR! | V9: ='Costi x asset'!H45/S9 -> #ERROR! | W9: ='Costi x asset'!K45/S9 -> #ERROR! | X9: ='Ricavi Gruppo x asset'!#REF! -> #ERROR! | Y9: ='Costi x asset'!C45/X9 -> #ERROR! | Z9: ='Costi x asset'!F45/X9 -> #ERROR! | AA9: ='Costi x asset'!I45/X9 -> #ERROR! | AB9: ='Costi x asset'!L45/X9 -> #ERROR! | AC9: ='Ricavi Gruppo x asset'!#REF! -> #ERROR! | AD9: ='Costi x asset'!D45/AC9 -> #ERROR! | AE9: ='Costi x asset'!G45/AC9 -> #ERROR! | AF9: ='Costi x asset'!J45/AC9 -> #ERROR! | AG9: ='Costi x asset'!M45/AC9 -> #ERROR!
A10: Luglio | B10: ='Ricavi Gruppo x asset'!B14 -> 0 | C10: ='Costi x asset'!B10/'incidenza costi-ricavi'!B10 -> #DIV/0! | D10: ='Costi x asset'!E10/'incidenza costi-ricavi'!B10 -> #DIV/0! | E10: ='Costi x asset'!H10/B10 -> #DIV/0! | F10: ='Costi x asset'!K10/B10 -> #DIV/0! | G10: ='Ricavi Gruppo x asset'!D14 -> 0 | H10: ='Costi x asset'!C10/'incidenza costi-ricavi'!G10 -> #DIV/0! | I10: ='Costi x asset'!F10/'incidenza costi-ricavi'!G10 -> #DIV/0! | J10: ='Costi x asset'!I10/'incidenza costi-ricavi'!G10 -> #DIV/0! | K10: ='Costi x asset'!L10/'incidenza costi-ricavi'!G10 -> #DIV/0! | L10: ='Ricavi Gruppo x asset'!F14 -> 0 | M10: ='Costi x asset'!D10/'incidenza costi-ricavi'!L10 -> #DIV/0! | N10: ='Costi x asset'!G10/'incidenza costi-ricavi'!L10 -> #DIV/0! | O10: ='Costi x asset'!J10/'incidenza costi-ricavi'!L10 -> #DIV/0! | P10: ='Costi x asset'!M10/'incidenza costi-ricavi'!L10 -> #DIV/0! | R10: Luglio | S10: ='Ricavi Gruppo x asset'!#REF! -> #ERROR! | T10: ='Costi x asset'!B46/S10 -> #ERROR! | U10: ='Costi x asset'!E46/S10 -> #ERROR! | V10: ='Costi x asset'!H46/S10 -> #ERROR! | W10: ='Costi x asset'!K46/S10 -> #ERROR! | X10: ='Ricavi Gruppo x asset'!#REF! -> #ERROR! | Y10: ='Costi x asset'!C46/X10 -> #ERROR! | Z10: ='Costi x asset'!F46/X10 -> #ERROR! | AA10: ='Costi x asset'!I46/X10 -> #ERROR! | AB10: ='Costi x asset'!L46/X10 -> #ERROR! | AC10: ='Ricavi Gruppo x asset'!#REF! -> #ERROR! | AD10: ='Costi x asset'!D46/AC10 -> #ERROR! | AE10: ='Costi x asset'!G46/AC10 -> #ERROR! | AF10: ='Costi x asset'!J46/AC10 -> #ERROR! | AG10: ='Costi x asset'!M46/AC10 -> #ERROR!
A11: Agosto | B11: ='Ricavi Gruppo x asset'!B16 -> 0 | C11: ='Costi x asset'!B11/'incidenza costi-ricavi'!B11 -> #DIV/0! | D11: ='Costi x asset'!E11/'incidenza costi-ricavi'!B11 -> #DIV/0! | E11: ='Costi x asset'!H11/B11 -> #DIV/0! | F11: ='Costi x asset'!K11/B11 -> #DIV/0! | G11: ='Ricavi Gruppo x asset'!D16 -> 0 | H11: ='Costi x asset'!C11/'incidenza costi-ricavi'!G11 -> #DIV/0! | I11: ='Costi x asset'!F11/'incidenza costi-ricavi'!G11 -> #DIV/0! | J11: ='Costi x asset'!I11/'incidenza costi-ricavi'!G11 -> #DIV/0! | K11: ='Costi x asset'!L11/'incidenza costi-ricavi'!G11 -> #DIV/0! | L11: ='Ricavi Gruppo x asset'!F16 -> 0 | M11: ='Costi x asset'!D11/'incidenza costi-ricavi'!L11 -> #DIV/0! | N11: ='Costi x asset'!G11/'incidenza costi-ricavi'!L11 -> #DIV/0! | O11: ='Costi x asset'!J11/'incidenza costi-ricavi'!L11 -> #DIV/0! | P11: ='Costi x asset'!M11/'incidenza costi-ricavi'!L11 -> #DIV/0! | R11: Agosto | S11: ='Ricavi Gruppo x asset'!#REF! -> #ERROR! | T11: ='Costi x asset'!B47/S11 -> #ERROR! | U11: ='Costi x asset'!E47/S11 -> #ERROR! | V11: ='Costi x asset'!H47/S11 -> #ERROR! | W11: ='Costi x asset'!K47/S11 -> #ERROR! | X11: ='Ricavi Gruppo x asset'!#REF! -> #ERROR! | Y11: ='Costi x asset'!C47/X11 -> #ERROR! | Z11: ='Costi x asset'!F47/X11 -> #ERROR! | AA11: ='Costi x asset'!I47/X11 -> #ERROR! | AB11: ='Costi x asset'!L47/X11 -> #ERROR! | AC11: ='Ricavi Gruppo x asset'!#REF! -> #ERROR! | AD11: ='Costi x asset'!D47/AC11 -> #ERROR! | AE11: ='Costi x asset'!G47/AC11 -> #ERROR! | AF11: ='Costi x asset'!J47/AC11 -> #ERROR! | AG11: ='Costi x asset'!M47/AC11 -> #ERROR!
A12: Settembre | B12: ='Ricavi Gruppo x asset'!B18 -> 0 | C12: ='Costi x asset'!B12/'incidenza costi-ricavi'!B12 -> #DIV/0! | D12: ='Costi x asset'!E12/'incidenza costi-ricavi'!B12 -> #DIV/0! | E12: ='Costi x asset'!H12/B12 -> #DIV/0! | F12: ='Costi x asset'!K12/B12 -> #DIV/0! | G12: ='Ricavi Gruppo x asset'!D18 -> 0 | H12: ='Costi x asset'!C12/'incidenza costi-ricavi'!G12 -> #DIV/0! | I12: ='Costi x asset'!F12/'incidenza costi-ricavi'!G12 -> #DIV/0! | J12: ='Costi x asset'!I12/'incidenza costi-ricavi'!G12 -> #DIV/0! | K12: ='Costi x asset'!L12/'incidenza costi-ricavi'!G12 -> #DIV/0! | L12: ='Ricavi Gruppo x asset'!F18 -> 0 | M12: ='Costi x asset'!D12/'incidenza costi-ricavi'!L12 -> #DIV/0! | N12: ='Costi x asset'!G12/'incidenza costi-ricavi'!L12 -> #DIV/0! | O12: ='Costi x asset'!J12/'incidenza costi-ricavi'!L12 -> #DIV/0! | P12: ='Costi x asset'!M12/'incidenza costi-ricavi'!L12 -> #DIV/0! | R12: Settembre | S12: ='Ricavi Gruppo x asset'!#REF! -> #ERROR! | T12: ='Costi x asset'!B48/S12 -> #ERROR! | U12: ='Costi x asset'!E48/S12 -> #ERROR! | V12: ='Costi x asset'!H48/S12 -> #ERROR! | W12: ='Costi x asset'!K48/S12 -> #ERROR! | X12: ='Ricavi Gruppo x asset'!#REF! -> #ERROR! | Y12: ='Costi x asset'!C48/X12 -> #ERROR! | Z12: ='Costi x asset'!F48/X12 -> #ERROR! | AA12: ='Costi x asset'!I48/X12 -> #ERROR! | AB12: ='Costi x asset'!L48/X12 -> #ERROR! | AC12: ='Ricavi Gruppo x asset'!#REF! -> #ERROR! | AD12: ='Costi x asset'!D48/AC12 -> #ERROR! | AE12: ='Costi x asset'!G48/AC12 -> #ERROR! | AF12: ='Costi x asset'!J48/AC12 -> #ERROR! | AG12: ='Costi x asset'!M48/AC12 -> #ERROR!
A13: Ottobre | B13: ='Ricavi Gruppo x asset'!B20 -> 0 | C13: ='Costi x asset'!B13/'incidenza costi-ricavi'!B13 -> #DIV/0! | D13: ='Costi x asset'!E13/'incidenza costi-ricavi'!B13 -> #DIV/0! | E13: ='Costi x asset'!H13/B13 -> #DIV/0! | F13: ='Costi x asset'!K13/B13 -> #DIV/0! | G13: ='Ricavi Gruppo x asset'!D20 -> 0 | H13: ='Costi x asset'!C13/'incidenza costi-ricavi'!G13 -> #DIV/0! | I13: ='Costi x asset'!F13/'incidenza costi-ricavi'!G13 -> #DIV/0! | J13: ='Costi x asset'!I13/'incidenza costi-ricavi'!G13 -> #DIV/0! | K13: ='Costi x asset'!L13/'incidenza costi-ricavi'!G13 -> #DIV/0! | L13: ='Ricavi Gruppo x asset'!F20 -> 0 | M13: ='Costi x asset'!D13/'incidenza costi-ricavi'!L13 -> #DIV/0! | N13: ='Costi x asset'!G13/'incidenza costi-ricavi'!L13 -> #DIV/0! | O13: ='Costi x asset'!J13/'incidenza costi-ricavi'!L13 -> #DIV/0! | P13: ='Costi x asset'!M13/'incidenza costi-ricavi'!L13 -> #DIV/0! | R13: Ottobre | S13: ='Ricavi Gruppo x asset'!#REF! -> #ERROR! | T13: ='Costi x asset'!B49/S13 -> #ERROR! | U13: ='Costi x asset'!E49/S13 -> #ERROR! | V13: ='Costi x asset'!H49/S13 -> #ERROR! | W13: ='Costi x asset'!K49/S13 -> #ERROR! | X13: ='Ricavi Gruppo x asset'!#REF! -> #ERROR! | Y13: ='Costi x asset'!C49/X13 -> #ERROR! | Z13: ='Costi x asset'!F49/X13 -> #ERROR! | AA13: ='Costi x asset'!I49/X13 -> #ERROR! | AB13: ='Costi x asset'!L49/X13 -> #ERROR! | AC13: ='Ricavi Gruppo x asset'!#REF! -> #ERROR! | AD13: ='Costi x asset'!D49/AC13 -> #ERROR! | AE13: ='Costi x asset'!G49/AC13 -> #ERROR! | AF13: ='Costi x asset'!J49/AC13 -> #ERROR! | AG13: ='Costi x asset'!M49/AC13 -> #ERROR!
A14: Novembre | B14: ='Ricavi Gruppo x asset'!B22 -> 0 | C14: ='Costi x asset'!B14/'incidenza costi-ricavi'!B14 -> #DIV/0! | D14: ='Costi x asset'!E14/'incidenza costi-ricavi'!B14 -> #DIV/0! | E14: ='Costi x asset'!H14/B14 -> #DIV/0! | F14: ='Costi x asset'!K14/B14 -> #DIV/0! | G14: ='Ricavi Gruppo x asset'!D22 -> 0 | H14: ='Costi x asset'!C14/'incidenza costi-ricavi'!G14 -> #DIV/0! | I14: ='Costi x asset'!F14/'incidenza costi-ricavi'!G14 -> #DIV/0! | J14: ='Costi x asset'!I14/'incidenza costi-ricavi'!G14 -> #DIV/0! | K14: ='Costi x asset'!L14/'incidenza costi-ricavi'!G14 -> #DIV/0! | L14: ='Ricavi Gruppo x asset'!F22 -> 0 | M14: ='Costi x asset'!D14/'incidenza costi-ricavi'!L14 -> #DIV/0! | N14: ='Costi x asset'!G14/'incidenza costi-ricavi'!L14 -> #DIV/0! | O14: ='Costi x asset'!J14/'incidenza costi-ricavi'!L14 -> #DIV/0! | P14: ='Costi x asset'!M14/'incidenza costi-ricavi'!L14 -> #DIV/0! | R14: Novembre | S14: ='Ricavi Gruppo x asset'!#REF! -> #ERROR! | T14: ='Costi x asset'!B50/S14 -> #ERROR! | U14: ='Costi x asset'!E50/S14 -> #ERROR! | V14: ='Costi x asset'!H50/S14 -> #ERROR! | W14: ='Costi x asset'!K50/S14 -> #ERROR! | X14: ='Ricavi Gruppo x asset'!#REF! -> #ERROR! | Y14: ='Costi x asset'!C50/X14 -> #ERROR! | Z14: ='Costi x asset'!F50/X14 -> #ERROR! | AA14: ='Costi x asset'!I50/X14 -> #ERROR! | AB14: ='Costi x asset'!L50/X14 -> #ERROR! | AC14: ='Ricavi Gruppo x asset'!#REF! -> #ERROR! | AD14: ='Costi x asset'!D50/AC14 -> #ERROR! | AE14: ='Costi x asset'!G50/AC14 -> #ERROR! | AF14: ='Costi x asset'!J50/AC14 -> #ERROR! | AG14: ='Costi x asset'!M50/AC14 -> #ERROR!
A15: Dicembre | B15: ='Ricavi Gruppo x asset'!B24 -> 0 | C15: ='Costi x asset'!B15/'incidenza costi-ricavi'!B15 -> #DIV/0! | D15: ='Costi x asset'!E15/'incidenza costi-ricavi'!B15 -> #DIV/0! | E15: ='Costi x asset'!H15/B15 -> #DIV/0! | F15: ='Costi x asset'!K15/B15 -> #DIV/0! | G15: ='Ricavi Gruppo x asset'!D24 -> 0 | H15: ='Costi x asset'!C15/'incidenza costi-ricavi'!G15 -> #DIV/0! | I15: ='Costi x asset'!F15/'incidenza costi-ricavi'!G15 -> #DIV/0! | J15: ='Costi x asset'!I15/'incidenza costi-ricavi'!G15 -> #DIV/0! | K15: ='Costi x asset'!L15/'incidenza costi-ricavi'!G15 -> #DIV/0! | L15: ='Ricavi Gruppo x asset'!F24 -> 0 | M15: ='Costi x asset'!D15/'incidenza costi-ricavi'!L15 -> #DIV/0! | N15: ='Costi x asset'!G15/'incidenza costi-ricavi'!L15 -> #DIV/0! | O15: ='Costi x asset'!J15/'incidenza costi-ricavi'!L15 -> #DIV/0! | P15: ='Costi x asset'!M15/'incidenza costi-ricavi'!L15 -> #DIV/0! | R15: Dicembre | S15: ='Ricavi Gruppo x asset'!#REF! -> #ERROR! | T15: ='Costi x asset'!B51/S15 -> #ERROR! | U15: ='Costi x asset'!E51/S15 -> #ERROR! | V15: ='Costi x asset'!H51/S15 -> #ERROR! | W15: ='Costi x asset'!K51/S15 -> #ERROR! | X15: ='Ricavi Gruppo x asset'!#REF! -> #ERROR! | Y15: ='Costi x asset'!C51/X15 -> #ERROR! | Z15: ='Costi x asset'!F51/X15 -> #ERROR! | AA15: ='Costi x asset'!I51/X15 -> #ERROR! | AB15: ='Costi x asset'!L51/X15 -> #ERROR! | AC15: ='Ricavi Gruppo x asset'!#REF! -> #ERROR! | AD15: ='Costi x asset'!D51/AC15 -> #ERROR! | AE15: ='Costi x asset'!G51/AC15 -> #ERROR! | AF15: ='Costi x asset'!J51/AC15 -> #ERROR! | AG15: ='Costi x asset'!M51/AC15 -> #ERROR!
A16: TOTALI | B16: =SUM(B4:B15) -> 0 | C16: ='Costi x asset'!B16/'incidenza costi-ricavi'!B16 -> #DIV/0! | D16: ='Costi x asset'!E16/B16 -> #DIV/0! | E16: ='Costi x asset'!H16/'incidenza costi-ricavi'!B16 -> #DIV/0! | F16: ='Costi x asset'!K16/'incidenza costi-ricavi'!B16 -> #DIV/0! | G16: =SUM(G4:G15) -> 0 | H16: ='Costi x asset'!C16/'incidenza costi-ricavi'!G16 -> #DIV/0! | I16: ='Costi x asset'!F16/'incidenza costi-ricavi'!G16 -> #DIV/0! | J16: ='Costi x asset'!I16/'incidenza costi-ricavi'!G16 -> #DIV/0! | K16: ='Costi x asset'!L16/'incidenza costi-ricavi'!G16 -> #DIV/0! | L16: =SUM(L4:L15) -> 0 | M16: ='Costi x asset'!D16/'incidenza costi-ricavi'!L16 -> #DIV/0! | N16: ='Costi x asset'!G16/'incidenza costi-ricavi'!L16 -> #DIV/0! | O16: ='Costi x asset'!J16/'incidenza costi-ricavi'!L16 -> #DIV/0! | P16: ='Costi x asset'!M16/'incidenza costi-ricavi'!L16 -> #DIV/0! | R16: TOTALI | S16: =SUM(S4:S15) -> #ERROR! | T16: ='Costi x asset'!B52/S16 -> #ERROR! | U16: ='Costi x asset'!E52/S16 -> #ERROR! | V16: ='Costi x asset'!H52/S16 -> #ERROR! | W16: ='Costi x asset'!K52/S16 -> #ERROR! | X16: =SUM(X4:X15) -> #ERROR! | Y16: ='Costi x asset'!C52/X16 -> #ERROR! | Z16: ='Costi x asset'!F52/X16 -> #ERROR! | AA16: ='Costi x asset'!I52/X16 -> #ERROR! | AB16: ='Costi x asset'!L52/X16 -> #ERROR! | AC16: =SUM(AC4:AC15) -> #ERROR! | AD16: ='Costi x asset'!D52/AC16 -> #ERROR! | AE16: ='Costi x asset'!G52/AC16 -> #ERROR! | AF16: ='Costi x asset'!J52/AC16 -> #ERROR! | AG16: ='Costi x asset'!M52/AC16 -> #ERROR!
B18: 2024 | G18: 2025 | L18: Budget
A19: C.V.M. | B19: Ricavi | C19: Costi (%) | G19: Ricavi | H19: Costi (%) | L19: Ricavi | M19: Costi (%)
B20: € | C20: Personale | D20: Produzione | E20: Gest. e Fin. | F20: Commerciale | G20: € | H20: Personale | I20: Produzione | J20: Gest. e Fin. | K20: Commerciale | L20: € | M20: Personale | N20: Produzione | O20: Gest. e Fin. | P20: Commerciale
A21: Gennaio | B21: ='Ricavi Gruppo x asset'!G3 -> 0 | C21: ='Costi x asset'!P4/B21 -> #DIV/0! | D21: ='Costi x asset'!S4/B21 -> #DIV/0! | E21: ='Costi x asset'!V4/B21 -> #DIV/0! | F21: ='Costi x asset'!Y4/B21 -> #DIV/0! | G21: ='Ricavi Gruppo x asset'!I3 -> 0 | H21: ='Costi x asset'!P4/G21 -> #DIV/0! | I21: ='Costi x asset'!S4/G21 -> #DIV/0! | J21: ='Costi x asset'!V4/G21 -> #DIV/0! | K21: ='Costi x asset'!Y4/G21 -> #DIV/0! | L21: ='Ricavi Gruppo x asset'!K3 -> 0 | M21: ='Costi x asset'!R4/'incidenza costi-ricavi'!L21 -> #DIV/0! | N21: ='Costi x asset'!U4/L21 -> #DIV/0! | O21: ='Costi x asset'!X4/L21 -> #DIV/0! | P21: ='Costi x asset'!AA4/L21 -> #DIV/0!
A22: Febbraio | B22: ='Ricavi Gruppo x asset'!G4 -> 0 | C22: ='Costi x asset'!P5/B22 -> #DIV/0! | D22: ='Costi x asset'!S5/B22 -> #DIV/0! | E22: ='Costi x asset'!V5/B22 -> #DIV/0! | F22: ='Costi x asset'!Y5/B22 -> #DIV/0! | G22: ='Ricavi Gruppo x asset'!I4 -> 0 | H22: ='Costi x asset'!P5/G22 -> #DIV/0! | I22: ='Costi x asset'!S5/G22 -> #DIV/0! | J22: ='Costi x asset'!V5/G22 -> #DIV/0! | K22: ='Costi x asset'!Y5/G22 -> #DIV/0! | L22: ='Ricavi Gruppo x asset'!K4 -> 0 | M22: ='Costi x asset'!R5/'incidenza costi-ricavi'!L22 -> #DIV/0! | N22: ='Costi x asset'!U5/L22 -> #DIV/0! | O22: ='Costi x asset'!X5/L22 -> #DIV/0! | P22: ='Costi x asset'!AA5/L22 -> #DIV/0!
A23: Marzo | B23: ='Ricavi Gruppo x asset'!G6 -> 0 | C23: ='Costi x asset'!P6/B23 -> #DIV/0! | D23: ='Costi x asset'!S6/B23 -> #DIV/0! | E23: ='Costi x asset'!V6/B23 -> #DIV/0! | F23: ='Costi x asset'!Y6/B23 -> #DIV/0! | G23: ='Ricavi Gruppo x asset'!I6 -> 0 | H23: ='Costi x asset'!P6/G23 -> #DIV/0! | I23: ='Costi x asset'!S6/G23 -> #DIV/0! | J23: ='Costi x asset'!V6/G23 -> #DIV/0! | K23: ='Costi x asset'!Y6/G23 -> #DIV/0! | L23: ='Ricavi Gruppo x asset'!K6 -> 0 | M23: ='Costi x asset'!R6/'incidenza costi-ricavi'!L23 -> #DIV/0! | N23: ='Costi x asset'!U6/L23 -> #DIV/0! | O23: ='Costi x asset'!X6/L23 -> #DIV/0! | P23: ='Costi x asset'!AA6/L23 -> #DIV/0!
A24: Aprile | B24: ='Ricavi Gruppo x asset'!G8 -> 0 | C24: ='Costi x asset'!P7/B24 -> #DIV/0! | D24: ='Costi x asset'!S7/B24 -> #DIV/0! | E24: ='Costi x asset'!V7/B24 -> #DIV/0! | F24: ='Costi x asset'!Y7/B24 -> #DIV/0! | G24: ='Ricavi Gruppo x asset'!I8 -> 0 | H24: ='Costi x asset'!P7/G24 -> #DIV/0! | I24: ='Costi x asset'!S7/G24 -> #DIV/0! | J24: ='Costi x asset'!V7/G24 -> #DIV/0! | K24: ='Costi x asset'!Y7/G24 -> #DIV/0! | L24: ='Ricavi Gruppo x asset'!K8 -> 0 | M24: ='Costi x asset'!R7/'incidenza costi-ricavi'!L24 -> #DIV/0! | N24: ='Costi x asset'!U7/L24 -> #DIV/0! | O24: ='Costi x asset'!X7/L24 -> #DIV/0! | P24: ='Costi x asset'!AA7/L24 -> #DIV/0!
A25: Maggio | B25: ='Ricavi Gruppo x asset'!G10 -> 0 | C25: ='Costi x asset'!P8/B25 -> #DIV/0! | D25: ='Costi x asset'!S8/B25 -> #DIV/0! | E25: ='Costi x asset'!V8/B25 -> #DIV/0! | F25: ='Costi x asset'!Y8/B25 -> #DIV/0! | G25: ='Ricavi Gruppo x asset'!I10 -> 0 | H25: ='Costi x asset'!P8/G25 -> #DIV/0! | I25: ='Costi x asset'!S8/G25 -> #DIV/0! | J25: ='Costi x asset'!V8/G25 -> #DIV/0! | K25: ='Costi x asset'!Y8/G25 -> #DIV/0! | L25: ='Ricavi Gruppo x asset'!K10 -> 0 | M25: ='Costi x asset'!R8/'incidenza costi-ricavi'!L25 -> #DIV/0! | N25: ='Costi x asset'!U8/L25 -> #DIV/0! | O25: ='Costi x asset'!X8/L25 -> #DIV/0! | P25: ='Costi x asset'!AA8/L25 -> #DIV/0!
A26: Giugno | B26: ='Ricavi Gruppo x asset'!G12 -> 0 | C26: ='Costi x asset'!P9/B26 -> #DIV/0! | D26: ='Costi x asset'!S9/B26 -> #DIV/0! | E26: ='Costi x asset'!V9/B26 -> #DIV/0! | F26: ='Costi x asset'!Y9/B26 -> #DIV/0! | G26: ='Ricavi Gruppo x asset'!I12 -> 0 | H26: ='Costi x asset'!P9/G26 -> #DIV/0! | I26: ='Costi x asset'!S9/G26 -> #DIV/0! | J26: ='Costi x asset'!V9/G26 -> #DIV/0! | K26: ='Costi x asset'!Y9/G26 -> #DIV/0! | L26: ='Ricavi Gruppo x asset'!K12 -> 0 | M26: ='Costi x asset'!R9/'incidenza costi-ricavi'!L26 -> #DIV/0! | N26: ='Costi x asset'!U9/L26 -> #DIV/0! | O26: ='Costi x asset'!X9/L26 -> #DIV/0! | P26: ='Costi x asset'!AA9/L26 -> #DIV/0!
A27: Luglio | B27: ='Ricavi Gruppo x asset'!G14 -> 0 | C27: ='Costi x asset'!P10/B27 -> #DIV/0! | D27: ='Costi x asset'!S10/B27 -> #DIV/0! | E27: ='Costi x asset'!V10/B27 -> #DIV/0! | F27: ='Costi x asset'!Y10/B27 -> #DIV/0! | G27: ='Ricavi Gruppo x asset'!I14 -> 0 | H27: ='Costi x asset'!P10/G27 -> #DIV/0! | I27: ='Costi x asset'!S10/G27 -> #DIV/0! | J27: ='Costi x asset'!V10/G27 -> #DIV/0! | K27: ='Costi x asset'!Y10/G27 -> #DIV/0! | L27: ='Ricavi Gruppo x asset'!K14 -> 0 | M27: ='Costi x asset'!R10/'incidenza costi-ricavi'!L27 -> #DIV/0! | N27: ='Costi x asset'!U10/L27 -> #DIV/0! | O27: ='Costi x asset'!X10/L27 -> #DIV/0! | P27: ='Costi x asset'!AA10/L27 -> #DIV/0!
A28: Agosto | B28: ='Ricavi Gruppo x asset'!G16 -> 0 | C28: ='Costi x asset'!P11/B28 -> #DIV/0! | D28: ='Costi x asset'!S11/B28 -> #DIV/0! | E28: ='Costi x asset'!V11/B28 -> #DIV/0! | F28: ='Costi x asset'!Y11/B28 -> #DIV/0! | G28: ='Ricavi Gruppo x asset'!I16 -> 0 | H28: ='Costi x asset'!P11/G28 -> #DIV/0! | I28: ='Costi x asset'!S11/G28 -> #DIV/0! | J28: ='Costi x asset'!V11/G28 -> #DIV/0! | K28: ='Costi x asset'!Y11/G28 -> #DIV/0! | L28: ='Ricavi Gruppo x asset'!K16 -> 0 | M28: ='Costi x asset'!R11/'incidenza costi-ricavi'!L28 -> #DIV/0! | N28: ='Costi x asset'!U11/L28 -> #DIV/0! | O28: ='Costi x asset'!X11/L28 -> #DIV/0! | P28: ='Costi x asset'!AA11/L28 -> #DIV/0!
A29: Settembre | B29: ='Ricavi Gruppo x asset'!G18 -> 0 | C29: ='Costi x asset'!P12/B29 -> #DIV/0! | D29: ='Costi x asset'!S12/B29 -> #DIV/0! | E29: ='Costi x asset'!V12/B29 -> #DIV/0! | F29: ='Costi x asset'!Y12/B29 -> #DIV/0! | G29: ='Ricavi Gruppo x asset'!I18 -> 0 | H29: ='Costi x asset'!P12/G29 -> #DIV/0! | I29: ='Costi x asset'!S12/G29 -> #DIV/0! | J29: ='Costi x asset'!V12/G29 -> #DIV/0! | K29: ='Costi x asset'!Y12/G29 -> #DIV/0! | L29: ='Ricavi Gruppo x asset'!K18 -> 0 | M29: ='Costi x asset'!R12/'incidenza costi-ricavi'!L29 -> #DIV/0! | N29: ='Costi x asset'!U12/L29 -> #DIV/0! | O29: ='Costi x asset'!X12/L29 -> #DIV/0! | P29: ='Costi x asset'!AA12/L29 -> #DIV/0!
A30: Ottobre | B30: ='Ricavi Gruppo x asset'!G20 -> 0 | C30: ='Costi x asset'!P13/B30 -> #DIV/0! | D30: ='Costi x asset'!S13/B30 -> #DIV/0! | E30: ='Costi x asset'!V13/B30 -> #DIV/0! | F30: ='Costi x asset'!Y13/B30 -> #DIV/0! | G30: ='Ricavi Gruppo x asset'!I20 -> 0 | H30: ='Costi x asset'!P13/G30 -> #DIV/0! | I30: ='Costi x asset'!S13/G30 -> #DIV/0! | J30: ='Costi x asset'!V13/G30 -> #DIV/0! | K30: ='Costi x asset'!Y13/G30 -> #DIV/0! | L30: ='Ricavi Gruppo x asset'!K20 -> 0 | M30: ='Costi x asset'!R13/'incidenza costi-ricavi'!L30 -> #DIV/0! | N30: ='Costi x asset'!U13/L30 -> #DIV/0! | O30: ='Costi x asset'!X13/L30 -> #DIV/0! | P30: ='Costi x asset'!AA13/L30 -> #DIV/0!
A31: Novembre | B31: ='Ricavi Gruppo x asset'!G22 -> 0 | C31: ='Costi x asset'!P14/B31 -> #DIV/0! | D31: ='Costi x asset'!S14/B31 -> #DIV/0! | E31: ='Costi x asset'!V14/B31 -> #DIV/0! | F31: ='Costi x asset'!Y14/B31 -> #DIV/0! | G31: ='Ricavi Gruppo x asset'!I22 -> 0 | H31: ='Costi x asset'!P14/G31 -> #DIV/0! | I31: ='Costi x asset'!S14/G31 -> #DIV/0! | J31: ='Costi x asset'!V14/G31 -> #DIV/0! | K31: ='Costi x asset'!Y14/G31 -> #DIV/0! | L31: ='Ricavi Gruppo x asset'!K22 -> 0 | M31: ='Costi x asset'!R14/'incidenza costi-ricavi'!L31 -> #DIV/0! | N31: ='Costi x asset'!U14/L31 -> #DIV/0! | O31: ='Costi x asset'!X14/L31 -> #DIV/0! | P31: ='Costi x asset'!AA14/L31 -> #DIV/0!
A32: Dicembre | B32: ='Ricavi Gruppo x asset'!G24 -> 0 | C32: ='Costi x asset'!P15/B32 -> #DIV/0! | D32: ='Costi x asset'!S15/B32 -> #DIV/0! | E32: ='Costi x asset'!V15/B32 -> #DIV/0! | F32: ='Costi x asset'!Y15/B32 -> #DIV/0! | G32: ='Ricavi Gruppo x asset'!I24 -> 0 | H32: ='Costi x asset'!P15/G32 -> #DIV/0! | I32: ='Costi x asset'!S15/G32 -> #DIV/0! | J32: ='Costi x asset'!V15/G32 -> #DIV/0! | K32: ='Costi x asset'!Y15/G32 -> #DIV/0! | L32: ='Ricavi Gruppo x asset'!K24 -> 0 | M32: ='Costi x asset'!R15/'incidenza costi-ricavi'!L32 -> #DIV/0! | N32: ='Costi x asset'!U15/L32 -> #DIV/0! | O32: ='Costi x asset'!X15/L32 -> #DIV/0! | P32: ='Costi x asset'!AA15/L32 -> #DIV/0!
A33: TOTALI | B33: =SUM(B21:B32) -> 0 | C33: ='Costi x asset'!B33/'incidenza costi-ricavi'!B33 -> #DIV/0! | D33: ='Costi x asset'!S16/B33 -> #DIV/0! | E33: ='Costi x asset'!V16/B33 -> #DIV/0! | F33: ='Costi x asset'!Y16/B33 -> #DIV/0! | G33: =SUM(G21:G32) -> 0 | H33: ='Costi x asset'!P16/G33 -> #DIV/0! | I33: ='Costi x asset'!S16/G33 -> #DIV/0! | J33: ='Costi x asset'!V16/G33 -> #DIV/0! | K33: ='Costi x asset'!Y16/G33 -> #DIV/0! | L33: =SUM(L21:L32) -> 0 | M33: ='Costi x asset'!R16/'incidenza costi-ricavi'!L33 -> #DIV/0! | N33: ='Costi x asset'!U16/L33 -> #DIV/0! | O33: ='Costi x asset'!X16/L33 -> #DIV/0! | P33: ='Costi x asset'!AA16/L33 -> #DIV/0!
